{"crs": 4326, "type": "FeatureCollection", "features": [{"geometry": {"type": "Point", "coordinates": [-6.9913905437483983, 52.547068571034849]}, "type": "Feature", "id": 2750, "properties": {"url": "/0000014123/0001/", "csv_file": "/data/month/14123_0001.csv", "station.name": "Coolroe", "value": 0.303, "datetime": "2020-11-16 09:15:00+00:00", "sensor.ref": "0001", "station.ref": "0000014123", "station.region_id": 5, "err_code": 99}}, {"geometry": {"type": "Point", "coordinates": [-8.2385540000000006, 53.361687000000003]}, "type": "Feature", "id": 841, "properties": {"url": "/0000026007/0003/", "csv_file": "/data/month/26007_0003.csv", "station.name": "Bellagill", "value": 12.920, "datetime": "2020-11-16 09:15:00+00:00", "sensor.ref": "0003", "station.ref": "0000026007", "station.region_id": 2, "err_code": 99}}, {"geometry": {"type": "Point", "coordinates": [-8.2753979999999885, 52.139550999999976]}, "type": "Feature", "id": 1820, "properties": {"url": "/0000018107/OD/", "csv_file": "/data/month/18107_OD.csv", "station.name": "Fermoy Bridge D/S", "value": 23.318, "datetime": "2020-11-16 09:15:00+00:00", "sensor.ref": "OD", "station.ref": "0000018107", "station.region_id": 15, "err_code": 99}}, {"geometry": {"type": "Point", "coordinates": [-6.2214409884620574, 53.798040678733329]}, "type": "Feature", "id": 1609, "properties": {"url": "/0000006060/1300/", "csv_file": "/data/month/06060_1300.csv", "station.name": "Port Oriel", "value": 919.650, "datetime": "2013-01-02 04:20:00+00:00", "sensor.ref": "1300", "station.ref": "0000006060", "station.region_id": 10, "err_code": 99}}, {"geometry": {"type": "Point", "coordinates": [-7.8051570000000003, 53.854401000000003]}, "type": "Feature", "id": 26, "properties": {"url": "/0000026009/0002/", "csv_file": "/data/month/26009_0002.csv", "station.name": "Bellantra Bridge", "value": 10.400, "datetime": "2020-11-16 09:15:00+00:00", "sensor.ref": "0002", "station.ref": "0000026009", "station.region_id": 1, "err_code": 99}}, {"geometry": {"type": "Point", "coordinates": [-8.9039999067458169, 52.179203121718217]}, "type": "Feature", "id": 1812, "properties": {"url": "/0000018110/0001/", "csv_file": "/data/month/18110_0001.csv", "station.name": "Kilbrin Road", "value": 0.853, "datetime": "2020-11-16 09:15:00+00:00", "sensor.ref": "0001", "station.ref": "0000018110", "station.region_id": 12, "err_code": 99}}, {"geometry": {"type": "Point", "coordinates": [-7.9868602329863343, 53.467425373316097]}, "type": "Feature", "id": 1674, "properties": {"url": "/0000026088/1300/", "csv_file": "/data/month/26088_1300.csv", "station.name": "Hodson's Bay", "value": -41.640, "datetime": "2013-01-02 18:31:03+00:00", "sensor.ref": "1300", "station.ref": "0000026088", "station.region_id": 2, "err_code": 99}}, {"geometry": {"type": "Point", "coordinates": [-7.8051570000000003, 53.854401000000003]}, "type": "Feature", "id": 27, "properties": {"url": "/0000026009/0003/", "csv_file": "/data/month/26009_0003.csv", "station.name": "Bellantra Bridge", "value": 12.700, "datetime": "2020-11-16 09:15:00+00:00", "sensor.ref": "0003", "station.ref": "0000026009", "station.region_id": 1, "err_code": 99}}, {"geometry": {"type": "Point", "coordinates": [-9.0231692366723735, 51.911606376955781]}, "type": "Feature", "id": 2918, "properties": {"url": "/0000019111/0012/", "csv_file": "/data/month/19111_0012.csv", "station.name": "Killaclug", "value": 8.900, "datetime": "2020-11-16 09:00:00+00:00", "sensor.ref": "0012", "station.ref": "0000019111", "station.region_id": 12, "err_code": 99}}, {"geometry": {"type": "Point", "coordinates": [-8.9039999067458169, 52.179203121718217]}, "type": "Feature", "id": 1813, "properties": {"url": "/0000018110/OD/", "csv_file": "/data/month/18110_OD.csv", "station.name": "Kilbrin Road", "value": 79.986, "datetime": "2020-11-16 09:15:00+00:00", "sensor.ref": "OD", "station.ref": "0000018110", "station.region_id": 12, "err_code": 99}}, {"geometry": {"type": "Point", "coordinates": [-8.0140629999999931, 52.523496000000002]}, "type": "Feature", "id": 2043, "properties": {"url": "/0000016005/0001/", "csv_file": "/data/month/16005_0001.csv", "station.name": "Aughnagross", "value": 0.485, "datetime": "2020-11-16 09:15:00+00:00", "sensor.ref": "0001", "station.ref": "0000016005", "station.region_id": 5, "err_code": 99}}, {"geometry": {"type": "Point", "coordinates": [-8.2627620000000004, 53.431764000000001]}, "type": "Feature", "id": 630, "properties": {"url": "/0000026005/OD/", "csv_file": "/data/month/26005_OD.csv", "station.name": "Derrycahill", "value": 44.949, "datetime": "2020-11-16 09:15:00+00:00", "sensor.ref": "OD", "station.ref": "0000026005", "station.region_id": 2, "err_code": 99}}, {"geometry": {"type": "Point", "coordinates": [-8.2627620000000004, 53.431764000000001]}, "type": "Feature", "id": 458, "properties": {"url": "/0000026005/0003/", "csv_file": "/data/month/26005_0003.csv", "station.name": "Derrycahill", "value": 12.820, "datetime": "2020-11-16 09:15:00+00:00", "sensor.ref": "0003", "station.ref": "0000026005", "station.region_id": 2, "err_code": 99}}, {"geometry": {"type": "Point", "coordinates": [-8.4660279999999997, 53.729357]}, "type": "Feature", "id": 1597, "properties": {"url": "/0000026006/0003/", "csv_file": "/data/month/26006_0003.csv", "station.name": "Willsbrook", "value": 12.970, "datetime": "2020-11-16 09:15:00+00:00", "sensor.ref": "0003", "station.ref": "0000026006", "station.region_id": 2, "err_code": 99}}, {"geometry": {"type": "Point", "coordinates": [-8.2385540000000006, 53.361687000000003]}, "type": "Feature", "id": 1074, "properties": {"url": "/0000026007/0001/", "csv_file": "/data/month/26007_0001.csv", "station.name": "Bellagill", "value": 2.368, "datetime": "2020-11-16 09:15:00+00:00", "sensor.ref": "0001", "station.ref": "0000026007", "station.region_id": 2, "err_code": 99}}, {"geometry": {"type": "Point", "coordinates": [-8.2385540000000006, 53.361687000000003]}, "type": "Feature", "id": 799, "properties": {"url": "/0000026007/OD/", "csv_file": "/data/month/26007_OD.csv", "station.name": "Bellagill", "value": 42.488, "datetime": "2020-11-16 09:15:00+00:00", "sensor.ref": "OD", "station.ref": "0000026007", "station.region_id": 2, "err_code": 99}}, {"geometry": {"type": "Point", "coordinates": [-8.5570310000000003, 53.897013999999999]}, "type": "Feature", "id": 871, "properties": {"url": "/0000026014/0003/", "csv_file": "/data/month/26014_0003.csv", "station.name": "Banada Bridge  Lung ", "value": 12.810, "datetime": "2020-11-16 09:00:00+00:00", "sensor.ref": "0003", "station.ref": "0000026014", "station.region_id": 1, "err_code": 99}}, {"geometry": {"type": "Point", "coordinates": [-7.9229370000000001, 52.357672999999998]}, "type": "Feature", "id": 1994, "properties": {"url": "/0000016009/0002/", "csv_file": "/data/month/16009_0002.csv", "station.name": "Caher Park", "value": 9.300, "datetime": "2020-11-16 09:00:00+00:00", "sensor.ref": "0002", "station.ref": "0000016009", "station.region_id": 5, "err_code": 99}}, {"geometry": {"type": "Point", "coordinates": [-7.9229370000000001, 52.357672999999998]}, "type": "Feature", "id": 1995, "properties": {"url": "/0000016009/0003/", "csv_file": "/data/month/16009_0003.csv", "station.name": "Caher Park", "value": 12.050, "datetime": "2020-11-16 09:00:00+00:00", "sensor.ref": "0003", "station.ref": "0000016009", "station.region_id": 5, "err_code": 99}}, {"geometry": {"type": "Point", "coordinates": [-8.5570310000000003, 53.897013999999999]}, "type": "Feature", "id": 939, "properties": {"url": "/0000026014/0001/", "csv_file": "/data/month/26014_0001.csv", "station.name": "Banada Bridge  Lung ", "value": 1.445, "datetime": "2020-11-16 09:15:00+00:00", "sensor.ref": "0001", "station.ref": "0000026014", "station.region_id": 1, "err_code": 99}}, {"geometry": {"type": "Point", "coordinates": [-9.1328050000000118, 52.096076000000004]}, "type": "Feature", "id": 1763, "properties": {"url": "/0000018113/0001/", "csv_file": "/data/month/18113_0001.csv", "station.name": "Ahane Bridge", "value": 1.054, "datetime": "2020-11-16 09:15:00+00:00", "sensor.ref": "0001", "station.ref": "0000018113", "station.region_id": 12, "err_code": 99}}, {"geometry": {"type": "Point", "coordinates": [-9.1328050000000118, 52.096076000000004]}, "type": "Feature", "id": 1764, "properties": {"url": "/0000018113/OD/", "csv_file": "/data/month/18113_OD.csv", "station.name": "Ahane Bridge", "value": 110.003, "datetime": "2020-11-16 09:15:00+00:00", "sensor.ref": "OD", "station.ref": "0000018113", "station.region_id": 12, "err_code": 99}}, {"geometry": {"type": "Point", "coordinates": [-8.4438421936649686, 51.901557638840366]}, "type": "Feature", "id": 2626, "properties": {"url": "/0000019160/0003/", "csv_file": "/data/month/19160_0003.csv", "station.name": "Currach Club", "value": 12.800, "datetime": "2020-11-16 09:00:00+00:00", "sensor.ref": "0003", "station.ref": "0000019160", "station.region_id": 6, "err_code": 99}}, {"geometry": {"type": "Point", "coordinates": [-7.9188661951064985, 53.886635663816314]}, "type": "Feature", "id": 905, "properties": {"url": "/0000026015/0001/", "csv_file": "/data/month/26015_0001.csv", "station.name": "Corrascoffy", "value": 1.064, "datetime": "2020-11-16 09:15:00+00:00", "sensor.ref": "0001", "station.ref": "0000026015", "station.region_id": 1, "err_code": 99}}, {"geometry": {"type": "Point", "coordinates": [-8.6810010000000055, 52.082986999999989]}, "type": "Feature", "id": 1836, "properties": {"url": "/0000018114/0001/", "csv_file": "/data/month/18114_0001.csv", "station.name": "Clashmorgan", "value": 0.769, "datetime": "2020-11-16 09:15:00+00:00", "sensor.ref": "0001", "station.ref": "0000018114", "station.region_id": 6, "err_code": 99}}, {"geometry": {"type": "Point", "coordinates": [-8.6810010000000055, 52.082986999999989]}, "type": "Feature", "id": 1837, "properties": {"url": "/0000018114/OD/", "csv_file": "/data/month/18114_OD.csv", "station.name": "Clashmorgan", "value": 116.540, "datetime": "2020-11-16 09:15:00+00:00", "sensor.ref": "OD", "station.ref": "0000018114", "station.region_id": 6, "err_code": 99}}, {"geometry": {"type": "Point", "coordinates": [-8.6251789999999993, 52.078048000000003]}, "type": "Feature", "id": 2153, "properties": {"url": "/0000018115/0001/", "csv_file": "/data/month/18115_0001.csv", "station.name": "Jordans Bridge", "value": 0.744, "datetime": "2020-11-16 09:15:00+00:00", "sensor.ref": "0001", "station.ref": "0000018115", "station.region_id": 6, "err_code": 99}}, {"geometry": {"type": "Point", "coordinates": [-8.5570310000000003, 53.897013999999999]}, "type": "Feature", "id": 1045, "properties": {"url": "/0000026014/0002/", "csv_file": "/data/month/26014_0002.csv", "station.name": "Banada Bridge  Lung ", "value": 8.900, "datetime": "2020-11-16 09:00:00+00:00", "sensor.ref": "0002", "station.ref": "0000026014", "station.region_id": 1, "err_code": 99}}, {"geometry": {"type": "Point", "coordinates": [-8.6826719999999984, 51.76523199999999]}, "type": "Feature", "id": 1594, "properties": {"url": "/0000020002/0002/", "csv_file": "/data/month/20002_0002.csv", "station.name": "Curranure", "value": 10.400, "datetime": "2020-11-16 09:00:00+00:00", "sensor.ref": "0002", "station.ref": "0000020002", "station.region_id": 6, "err_code": 99}}, {"geometry": {"type": "Point", "coordinates": [-8.2719529999999999, 52.139719999999997]}, "type": "Feature", "id": 2157, "properties": {"url": "/0000018117/0001/", "csv_file": "/data/month/18117_0001.csv", "station.name": "Fermoy Mill", "value": 2.177, "datetime": "2020-11-16 09:15:00+00:00", "sensor.ref": "0001", "station.ref": "0000018117", "station.region_id": 15, "err_code": 99}}, {"geometry": {"type": "Point", "coordinates": [-8.6826719999999984, 51.76523199999999]}, "type": "Feature", "id": 1567, "properties": {"url": "/0000020002/0001/", "csv_file": "/data/month/20002_0001.csv", "station.name": "Curranure", "value": 1.021, "datetime": "2020-11-16 09:15:00+00:00", "sensor.ref": "0001", "station.ref": "0000020002", "station.region_id": 6, "err_code": 99}}, {"geometry": {"type": "Point", "coordinates": [-9.0978870000000001, 51.724699000000001]}, "type": "Feature", "id": 2497, "properties": {"url": "/0000020008/0001/", "csv_file": "/data/month/20008_0001.csv", "station.name": "Long Bridge Dunmanway", "value": 0.089, "datetime": "2020-11-16 09:15:00+00:00", "sensor.ref": "0001", "station.ref": "0000020008", "station.region_id": 12, "err_code": 99}}, {"geometry": {"type": "Point", "coordinates": [-9.0757589999999997, 51.709435999999997]}, "type": "Feature", "id": 2476, "properties": {"url": "/0000020016/0001/", "csv_file": "/data/month/20016_0001.csv", "station.name": "Bealaboy Bridge", "value": 0.824, "datetime": "2020-11-16 09:15:00+00:00", "sensor.ref": "0001", "station.ref": "0000020016", "station.region_id": 12, "err_code": 99}}, {"geometry": {"type": "Point", "coordinates": [-8.5122839999999993, 53.705593]}, "type": "Feature", "id": 1671, "properties": {"url": "/0000026004/0003/", "csv_file": "/data/month/26004_0003.csv", "station.name": "Bookala", "value": 12.960, "datetime": "2020-11-16 09:15:00+00:00", "sensor.ref": "0003", "station.ref": "0000026004", "station.region_id": 2, "err_code": 99}}, {"geometry": {"type": "Point", "coordinates": [-7.8476053053681065, 51.957226127432868]}, "type": "Feature", "id": 2604, "properties": {"url": "/0000018061/0003/", "csv_file": "/data/month/18061_0003.csv", "station.name": "Youghal Quay", "value": 12.900, "datetime": "2020-11-16 09:00:00+00:00", "sensor.ref": "0003", "station.ref": "0000018061", "station.region_id": 15, "err_code": 99}}, {"geometry": {"type": "Point", "coordinates": [-8.4602500000000003, 52.173699999999997]}, "type": "Feature", "id": 1990, "properties": {"url": "/0000018102/0002/", "csv_file": "/data/month/18102_0002.csv", "station.name": "Castletownroche Weir", "value": 9.500, "datetime": "2020-11-16 09:00:00+00:00", "sensor.ref": "0002", "station.ref": "0000018102", "station.region_id": 15, "err_code": 99}}, {"geometry": {"type": "Point", "coordinates": [-8.2627620000000004, 53.431764000000001]}, "type": "Feature", "id": 459, "properties": {"url": "/0000026005/0001/", "csv_file": "/data/month/26005_0001.csv", "station.name": "Derrycahill", "value": 2.289, "datetime": "2020-11-16 09:15:00+00:00", "sensor.ref": "0001", "station.ref": "0000026005", "station.region_id": 2, "err_code": 99}}, {"geometry": {"type": "Point", "coordinates": [-9.0978870000000001, 51.724699000000001]}, "type": "Feature", "id": 2499, "properties": {"url": "/0000020008/0002/", "csv_file": "/data/month/20008_0002.csv", "station.name": "Long Bridge Dunmanway", "value": 9.000, "datetime": "2020-11-16 09:00:00+00:00", "sensor.ref": "0002", "station.ref": "0000020008", "station.region_id": 12, "err_code": 99}}, {"geometry": {"type": "Point", "coordinates": [-9.0757589999999997, 51.709435999999997]}, "type": "Feature", "id": 2478, "properties": {"url": "/0000020016/0003/", "csv_file": "/data/month/20016_0003.csv", "station.name": "Bealaboy Bridge", "value": 12.900, "datetime": "2020-11-16 09:00:00+00:00", "sensor.ref": "0003", "station.ref": "0000020016", "station.region_id": 12, "err_code": 99}}, {"geometry": {"type": "Point", "coordinates": [-8.0140629999999931, 52.523496000000002]}, "type": "Feature", "id": 2044, "properties": {"url": "/0000016005/OD/", "csv_file": "/data/month/16005_OD.csv", "station.name": "Aughnagross", "value": 70.897, "datetime": "2020-11-16 09:15:00+00:00", "sensor.ref": "OD", "station.ref": "0000016005", "station.region_id": 5, "err_code": 99}}, {"geometry": {"type": "Point", "coordinates": [-8.0222960000000025, 52.519468999999972]}, "type": "Feature", "id": 2039, "properties": {"url": "/0000016006/0001/", "csv_file": "/data/month/16006_0001.csv", "station.name": "Ballinaclogh", "value": 0.727, "datetime": "2020-11-16 09:15:00+00:00", "sensor.ref": "0001", "station.ref": "0000016006", "station.region_id": 5, "err_code": 99}}, {"geometry": {"type": "Point", "coordinates": [-7.9978899999999999, 52.459470000000003]}, "type": "Feature", "id": 2124, "properties": {"url": "/0000016008/0001/", "csv_file": "/data/month/16008_0001.csv", "station.name": "New Bridge  Suir ", "value": 1.695, "datetime": "2020-11-16 09:15:00+00:00", "sensor.ref": "0001", "station.ref": "0000016008", "station.region_id": 5, "err_code": 99}}, {"geometry": {"type": "Point", "coordinates": [-7.9978899999999999, 52.459470000000003]}, "type": "Feature", "id": 2125, "properties": {"url": "/0000016008/OD/", "csv_file": "/data/month/16008_OD.csv", "station.name": "New Bridge  Suir ", "value": 56.645, "datetime": "2020-11-16 09:15:00+00:00", "sensor.ref": "OD", "station.ref": "0000016008", "station.region_id": 5, "err_code": 99}}, {"geometry": {"type": "Point", "coordinates": [-9.0289949999999912, 52.08962199999997]}, "type": "Feature", "id": 1830, "properties": {"url": "/0000018112/0003/", "csv_file": "/data/month/18112_0003.csv", "station.name": "Keale Bridge", "value": 12.300, "datetime": "2020-11-16 09:00:00+00:00", "sensor.ref": "0003", "station.ref": "0000018112", "station.region_id": 12, "err_code": 99}}, {"geometry": {"type": "Point", "coordinates": [-7.1279229067489087, 52.224183150713415]}, "type": "Feature", "id": 359, "properties": {"url": "/0000016115/OD/", "csv_file": "/data/month/16115_OD.csv", "station.name": "Sheep's Bridge Weir", "value": 5.164, "datetime": "2020-11-16 09:15:00+00:00", "sensor.ref": "OD", "station.ref": "0000016115", "station.region_id": 5, "err_code": 99}}, {"geometry": {"type": "Point", "coordinates": [-8.405722999999993, 52.248570999999977]}, "type": "Feature", "id": 1551, "properties": {"url": "/0000018024/0001/", "csv_file": "/data/month/18024_0001.csv", "station.name": "Glenavuddig Bridge", "value": 0.610, "datetime": "2020-11-16 09:15:00+00:00", "sensor.ref": "0001", "station.ref": "0000018024", "station.region_id": 15, "err_code": 99}}, {"geometry": {"type": "Point", "coordinates": [-8.6410370000000007, 52.132218000000002]}, "type": "Feature", "id": 2150, "properties": {"url": "/0000018057/OD/", "csv_file": "/data/month/18057_OD.csv", "station.name": "Mallow Town Bridge D/S", "value": 45.488, "datetime": "2020-11-16 09:15:00+00:00", "sensor.ref": "OD", "station.ref": "0000018057", "station.region_id": 12, "err_code": 99}}, {"geometry": {"type": "Point", "coordinates": [-7.8476053053681065, 51.957226127432868]}, "type": "Feature", "id": 2603, "properties": {"url": "/0000018061/0001/", "csv_file": "/data/month/18061_0001.csv", "station.name": "Youghal Quay", "value": 2.960, "datetime": "2020-11-16 09:15:00+00:00", "sensor.ref": "0001", "station.ref": "0000018061", "station.region_id": 15, "err_code": 99}}, {"geometry": {"type": "Point", "coordinates": [-7.8476053053681065, 51.957226127432868]}, "type": "Feature", "id": 2766, "properties": {"url": "/0000018061/OD/", "csv_file": "/data/month/18061_OD.csv", "station.name": "Youghal Quay", "value": -0.208, "datetime": "2020-11-16 09:15:00+00:00", "sensor.ref": "OD", "station.ref": "0000018061", "station.region_id": 15, "err_code": 99}}, {"geometry": {"type": "Point", "coordinates": [-8.2766339999999996, 52.138567999999999]}, "type": "Feature", "id": 2344, "properties": {"url": "/0000018106/0001/", "csv_file": "/data/month/18106_0001.csv", "station.name": "Fermoy Bridge U/S", "value": 0.680, "datetime": "2020-11-16 09:15:00+00:00", "sensor.ref": "0001", "station.ref": "0000018106", "station.region_id": 15, "err_code": 99}}, {"geometry": {"type": "Point", "coordinates": [-8.2766339999999996, 52.138567999999999]}, "type": "Feature", "id": 2345, "properties": {"url": "/0000018106/OD/", "csv_file": "/data/month/18106_OD.csv", "station.name": "Fermoy Bridge U/S", "value": 24.600, "datetime": "2020-11-16 09:15:00+00:00", "sensor.ref": "OD", "station.ref": "0000018106", "station.region_id": 15, "err_code": 99}}, {"geometry": {"type": "Point", "coordinates": [-8.2753979999999885, 52.139550999999976]}, "type": "Feature", "id": 1819, "properties": {"url": "/0000018107/0001/", "csv_file": "/data/month/18107_0001.csv", "station.name": "Fermoy Bridge D/S", "value": 1.398, "datetime": "2020-11-16 09:15:00+00:00", "sensor.ref": "0001", "station.ref": "0000018107", "station.region_id": 15, "err_code": 99}}, {"geometry": {"type": "Point", "coordinates": [-6.5502220000000104, 52.548512999999993]}, "type": "Feature", "id": 1498, "properties": {"url": "/0000012001/0001/", "csv_file": "/data/month/12001_0001.csv", "station.name": "Scaraw